cubicweb_graphql/__init__.py
cubicweb_graphql/__pkginfo__.py
cubicweb_graphql/gql_schema.py
cubicweb_graphql/hooks.py
cubicweb_graphql/querier.py
cubicweb_graphql/resolver.py
cubicweb_graphql/utils.py
cubicweb_graphql/views.py
cubicweb_graphql/i18n/en.po
cubicweb_graphql/i18n/es.po
cubicweb_graphql/i18n/fr.po
cubicweb_graphql-0.2.2.dist-info/METADATA
cubicweb_graphql-0.2.2.dist-info/WHEEL
cubicweb_graphql-0.2.2.dist-info/entry_points.txt
cubicweb_graphql-0.2.2.dist-info/top_level.txt
cubicweb_graphql-0.2.2.dist-info/RECORD
