Metadata-Version: 2.1
Name: cubicweb-graphql
Version: 0.2.2
Summary: GraphQL for CubicWeb
Home-page: https://www.cubicweb.org/project/cubicweb-graphql
Author: LOGILAB S.A. (Paris, FRANCE)
Author-email: contact@logilab.fr
License: LGPL
Platform: UNKNOWN
Classifier: Environment :: Web Environment
Classifier: Framework :: CubicWeb
Classifier: Programming Language :: Python
Classifier: Programming Language :: JavaScript
Requires-Dist: cubicweb (~=3.26)
Requires-Dist: six (>=1.12.0)
Requires-Dist: graphql-core (<3,>=2.3)
Requires-Dist: graphene (<3,>=2.1)
Requires-Dist: iso8601
